co2mpas/__init__.py
co2mpas/__main__.py
co2mpas/batch.py
co2mpas/co2mpas_output_template.xlsx
co2mpas/co2mpas_template.xlsx
co2mpas/conf.py
co2mpas/datasync.py
co2mpas/datasync_template.xlsx
co2mpas/docoptutils.py
co2mpas/plan.py
co2mpas/plot.py
co2mpas/report.py
co2mpas/_vendor/__init__.py
co2mpas/_vendor/rainbow_logging_handler.py
co2mpas/co2mparable/__init__.py
co2mpas/co2mparable/co2hasher.py
co2mpas/co2mparable/hasher.py
co2mpas/demos/co2mpas_demo-1.xlsx
co2mpas/demos/co2mpas_simplan.xlsx
co2mpas/io/__init__.py
co2mpas/io/constants.py
co2mpas/io/dill.py
co2mpas/io/excel.py
co2mpas/io/schema.py
co2mpas/io/ta.py
co2mpas/io/ta_mandatory.py
co2mpas/io/validations.py
co2mpas/ipynbs/simVehicle.ipynb
co2mpas/model/__init__.py
co2mpas/model/physical/__init__.py
co2mpas/model/physical/defaults.py
co2mpas/model/physical/final_drive.py
co2mpas/model/physical/vehicle.py
co2mpas/model/physical/wheels.py
co2mpas/model/physical/clutch_tc/__init__.py
co2mpas/model/physical/clutch_tc/clutch.py
co2mpas/model/physical/clutch_tc/torque_converter.py
co2mpas/model/physical/cycle/NEDC.py
co2mpas/model/physical/cycle/WLTP.py
co2mpas/model/physical/cycle/__init__.py
co2mpas/model/physical/electrics/__init__.py
co2mpas/model/physical/electrics/electrics_prediction.py
co2mpas/model/physical/engine/__init__.py
co2mpas/model/physical/engine/co2_emission.py
co2mpas/model/physical/engine/cold_start.py
co2mpas/model/physical/engine/start_stop.py
co2mpas/model/physical/engine/thermal.py
co2mpas/model/physical/gear_box/__init__.py
co2mpas/model/physical/gear_box/at_gear.py
co2mpas/model/physical/gear_box/cvt.py
co2mpas/model/physical/gear_box/manual_gear.py
co2mpas/model/physical/gear_box/mechanical.py
co2mpas/model/physical/gear_box/thermal.py
co2mpas/model/selector/__init__.py
co2mpas/model/selector/co2_params.py
co2mpas/utils/__init__.py
co2mpas/utils/logconfutils.py
co2mpas/utils/oscmd.py
co2sim-3.0.0.dist-info/METADATA
co2sim-3.0.0.dist-info/RECORD
co2sim-3.0.0.dist-info/WHEEL
co2sim-3.0.0.dist-info/entry_points.txt
co2sim-3.0.0.dist-info/top_level.txt
co2sim-3.0.0.dist-info/zip-safe
